kube_secrets/__init__.py
kube_secrets/cli.py
kube_secrets-0.0.1.dist-info/METADATA
kube_secrets-0.0.1.dist-info/WHEEL
kube_secrets-0.0.1.dist-info/entry_points.txt
kube_secrets-0.0.1.dist-info/top_level.txt
kube_secrets-0.0.1.dist-info/RECORD
